<?xml version="1.0" encoding="UTF-8"?>
<map xmlns:xsi="http://www.w3.org/2001/XMLSchema-instance">
    <interface bound="inbound" id="MYDCISCTCN0050401" version="1" />
    <src_io id="SMYDCTCN0050401" />
    <target_io id="TCISCTCN0050401" />
    <mapping>
        <source path="entity/ciVal" />
        <target path="entity/ciVal" />
        <function ref="move" />
    </mapping>
    <mapping>
        <source path="entity/trdInntNo" />
        <target path="entity/trdInntNo" />
        <function ref="move" />
    </mapping>
    <mapping>
        <source path="entity/apiGbcd" />
        <target path="entity/apiGbcd" />
        <function ref="move" />
    </mapping>
    <mapping>
        <source path="entity/istnCd" />
        <target path="entity/istnCd" />
        <function ref="move" />
    </mapping>
    <mapping>
        <source path="entity/qryDtm" />
        <target path="entity/qryDtm" />
        <function ref="move" />
    </mapping>
</map>
