<?xml version="1.0" encoding="UTF-8"?>
<map xmlns:xsi="http://www.w3.org/2001/XMLSchema-instance">
    <interface bound="outbound" id="SUICISUPEA0060101" version="1" />
    <src_io id="SSUIUPEA0060101" />
    <target_io id="TCISUPEA0060101" />
    <mapping>
        <source path="entity/CMISR_QRY_LST_ROWCOUNT" />
        <target path="entity/CMISR_QRY_LST_ROWCOUNT" />
        <function ref="move" />
    </mapping>
    <mapping>
        <source path="entity/CMISR_QRY_LST_LIST/CLLCTN_CUST_MNG_NO" />
        <target path="entity/CMISR_QRY_LST_LIST/CLLCTN_CUST_MNG_NO" />
        <function ref="move" />
    </mapping>
    <mapping>
        <source path="entity/CMISR_QRY_LST_LIST/CMIS_MNG_NO" />
        <target path="entity/CMISR_QRY_LST_LIST/CMIS_MNG_NO" />
        <function ref="move" />
    </mapping>
    <mapping>
        <source path="entity/CMISR_QRY_LST_LIST/CMIS_EVAL_STOTTR_MTHS" />
        <target path="entity/CMISR_QRY_LST_LIST/CMIS_EVAL_STOTTR_MTHS" />
        <function ref="move" />
    </mapping>
    <mapping>
        <source path="entity/CMISR_QRY_LST_LIST/OVPR_END_MTHS" />
        <target path="entity/CMISR_QRY_LST_LIST/OVPR_END_MTHS" />
        <function ref="move" />
    </mapping>
    <mapping>
        <source path="entity/CMISR_QRY_LST_LIST/CMISR" />
        <target path="entity/CMISR_QRY_LST_LIST/CMISR" />
        <function ref="move" />
    </mapping>
</map>
